lenzm_utils/__init__.py
lenzm_utils/_duration.py
lenzm_utils/bootstrap_wtf.py
lenzm_utils/comparable_mixin.py
lenzm_utils/dates.py
lenzm_utils/dicts.py
lenzm_utils/fontawesome.py
lenzm_utils/itertools.py
lenzm_utils/other.py
lenzm_utils/parse_string.py
lenzm_utils/sqlalchemy.py
lenzm_utils/web.py
lenzm_utils/flask/__init__.py
lenzm_utils/flask/url_converters.py
lenzm_utils/flask/url_for_obj.py
lenzm_utils/flask/url_update.py
lenzm_utils/flask/db_admin/__init__.py
lenzm_utils/flask/db_admin/migrate.py
lenzm_utils/flask/db_admin/pg.py
lenzm_utils-0.12.4.dist-info/LICENSE
lenzm_utils-0.12.4.dist-info/METADATA
lenzm_utils-0.12.4.dist-info/WHEEL
lenzm_utils-0.12.4.dist-info/top_level.txt
lenzm_utils-0.12.4.dist-info/RECORD
