Metadata-Version: 2.1
Name: lenzm-utils
Version: 0.12.4
Summary: Various utils including Flask projects
Home-page: https://github.com/mlenzen/lenzm_utils
Author: Michael Lenzen
Author-email: m.lenzen@gmail.com
License: MIT
Platform: UNKNOWN
Classifier: Development Status :: 3 - Alpha
Classifier: Intended Audience :: Developers
Classifier: Topic :: Software Development
Classifier: License :: OSI Approved :: BSD License
Classifier: Programming Language :: Python :: 3
Classifier: Programming Language :: Python :: 3.6
Classifier: Programming Language :: Python :: 3.7
Classifier: Programming Language :: Python :: 3.8
Requires-Dist: setuptools
Provides-Extra: all
Requires-Dist: Flask (>=0.11) ; extra == 'all'
Requires-Dist: SQLAlchemy ; extra == 'all'
Requires-Dist: Flask-SQLAlchemy ; extra == 'all'
Requires-Dist: alembic ; extra == 'all'
Requires-Dist: click ; extra == 'all'
Requires-Dist: wtforms ; extra == 'all'
Requires-Dist: collections-extended ; extra == 'all'
Requires-Dist: openpyxl ; extra == 'all'
Requires-Dist: pytz ; extra == 'all'
Requires-Dist: chardet ; extra == 'all'
